LICENSE
MANIFEST.in
README.md
setup.cfg
setup.py
lib/uskit/.database.py.swp
lib/uskit/.query_service.py.swp
lib/uskit/.server.py.swp
lib/uskit/.txn_service.py.swp
lib/uskit/__init__.py
lib/uskit/database.json
lib/uskit/database.py
lib/uskit/debug.py
lib/uskit/dynamic_record.py
lib/uskit/errors.py
lib/uskit/event_manager.py
lib/uskit/expression.py
lib/uskit/query.py
lib/uskit/query_service.py
lib/uskit/server.py
lib/uskit/service.py
lib/uskit/session.py
lib/uskit/txn_service.py
lib/uskit/util.py
lib/uskit.egg-info/PKG-INFO
lib/uskit.egg-info/SOURCES.txt
lib/uskit.egg-info/dependency_links.txt
lib/uskit.egg-info/requires.txt
lib/uskit.egg-info/top_level.txt
lib/uskit/static/.query_client.js.swp
lib/uskit/static/.txn_client.js.swp
lib/uskit/static/connectors.js
lib/uskit/static/debug.js
lib/uskit/static/event_manager.js
lib/uskit/static/index.js
lib/uskit/static/query_client.js
lib/uskit/static/session.js
lib/uskit/static/txn_client.js
lib/uskit/static/util.js
lib/uskit/static/widget/default-theme.css
lib/uskit/static/widget/dialog.css
lib/uskit/static/widget/dialog.html
lib/uskit/static/widget/dialog.js
lib/uskit/static/widget/filter.css
lib/uskit/static/widget/filter.html
lib/uskit/static/widget/filter.js
lib/uskit/static/widget/page.css
lib/uskit/static/widget/page.html
lib/uskit/static/widget/page.js
lib/uskit/static/widget/table.css
lib/uskit/static/widget/table.html
lib/uskit/static/widget/table.js
lib/uskit/static/widget/table_element.js
lib/uskit/static/widget/util.js
lib/uskit/static/widget/widget.css
lib/uskit/static/widget/widget.js