Metadata-Version: 2.1
Name: uskit
Version: 0.0.2
Summary: A microservices kit
Home-page: https://github.com/markuskimius/uskit
Author: Mark Kim
Author-email: markuskimius+py@gmail.com
License: Apache 2.0
Keywords: microservice,framework
Platform: UNKNOWN
License-File: LICENSE
